MANIFEST.in
README.md
setup.py
lpl/__init__.py
lpl/gameList.py
lpl/gameNews.py
lpl/lpl.py
lpl/settings.py
lpl/teamScore.py
lpl.egg-info/PKG-INFO
lpl.egg-info/SOURCES.txt
lpl.egg-info/dependency_links.txt
lpl.egg-info/entry_points.txt
lpl.egg-info/requires.txt
lpl.egg-info/top_level.txt
lpl.egg-info/zip-safe