Metadata-Version: 1.0
Name: lpl
Version: 0.2
Summary: lpl game based on Python
Home-page: https://github.com/wjhtime/lpl
Author: wjh
Author-email: wjhokey@gmail.com
License: MIT
Keywords: lpl,lol
Platform: UNKNOWN
